setup.py
pack_command/__init__.py
pack_command/_backup.py
pack_command/_speedups.c
pack_command.egg-info/PKG-INFO
pack_command.egg-info/SOURCES.txt
pack_command.egg-info/dependency_links.txt
pack_command.egg-info/top_level.txt