Metadata-Version: 1.1
Name: pack-command
Version: 0.2.1
Summary: Implements a faster Redis pack_command
Home-page: https://github.com/simonz05/pack-command/
Author: Simon Zimmermann
Author-email: simon@insmo.com
License: MIT
Keywords: redis
Platform: any
Classifier: Development Status :: 2 - Pre-Alpha
Classifier: Intended Audience :: Developers
Classifier: License :: OSI Approved :: MIT License
Classifier: Operating System :: POSIX
Classifier: Programming Language :: Python
Classifier: Topic :: Software Development
Classifier: Topic :: Software Development :: Libraries
